uk_public_services_imputation/__init__.py
uk_public_services_imputation/input_data.py
uk_public_services_imputation/main.py
uk_public_services_imputation/qrf.py
uk_public_services_imputation/data/__init__.py
uk_public_services_imputation/data/nhs_consumption_by_age_gender.csv
uk_public_services_imputation/data/.cache/huggingface/.gitignore
uk_public_services_imputation/data/.cache/huggingface/download/householdv2_1977-2021.tab.lock
uk_public_services_imputation/data/.cache/huggingface/download/householdv2_1977-2021.tab.metadata
uk_public_services_imputation/etb/impute_services.py
uk_public_services_imputation/nhs/impute_nhs_consumption.py
uk_public_services_imputation-0.1.2.dist-info/METADATA
uk_public_services_imputation-0.1.2.dist-info/WHEEL
uk_public_services_imputation-0.1.2.dist-info/entry_points.txt
uk_public_services_imputation-0.1.2.dist-info/RECORD
